vl_datasets/__init__.py
vl_datasets/image_folder.py
vl_datasets/sentry.py
vl_datasets/vl_food101.py
vl_datasets/vl_oxford_iiit_pet.py
vl_datasets-0.0.11.dist-info/LICENSE
vl_datasets-0.0.11.dist-info/METADATA
vl_datasets-0.0.11.dist-info/WHEEL
vl_datasets-0.0.11.dist-info/top_level.txt
vl_datasets-0.0.11.dist-info/RECORD
