Metadata-Version: 2.1
Name: vl-datasets
Version: 0.0.11
Summary: Open, Clean Datasets for Computer Vision.
Home-page: https://github.com/visual-layer/vl-datasets
Author: Visual Layer
Author-email: info@visual-layer.com
License: Apache-2.0
Keywords: machine learning,computer vision,data-centric
Platform: UNKNOWN
Classifier: License :: OSI Approved :: Apache Software License
Classifier: Programming Language :: Python :: 3.7
Classifier: Programming Language :: Python :: 3.8
Classifier: Programming Language :: Python :: 3.9
Classifier: Programming Language :: Python :: 3.10
Classifier: Operating System :: OS Independent
Requires-Python: >=3.7
License-File: LICENSE
Requires-Dist: torch
Requires-Dist: torchvision
Requires-Dist: pandas
Requires-Dist: sentry-sdk
